tfanalyse/change.py
tfanalyse/cli.py
tfanalyse/util.py
tfanalyse-0.2.0.dist-info/LICENSE.txt
tfanalyse-0.2.0.dist-info/METADATA
tfanalyse-0.2.0.dist-info/WHEEL
tfanalyse-0.2.0.dist-info/entry_points.txt
tfanalyse-0.2.0.dist-info/RECORD
